[1,["a591IlP8RI07+zNC2sfXuu","9bpZb6TR1C6reWa8VDyvrT","20ZaAAeqpNOaerku7TQcM2","3eylZNDjhDF64HKu4HxuEW","8aFmX13uRP1IKRH73xeC7+","309mXjKzBCF6iWE098ph0R","50Uw+SjzVK26CooZ4HNjnp","d1gCeXRKtCAr8syBuKKSmb","fdJzqJNNtG4KCl5FTBgutC","0awD8hdwZGkqHa4gpwNM0c","d7xi7wq+lM1b22hlaTyQSC"],["_textureSetter","shards01-0","shards01-1","shards01-2","shards01-3","shards01-4","shards01-5","shards01-6","shards01-7","shards01-8","shards01-9"],["cc.SpriteFrame",["cc.SpriteAtlas",["_name","_spriteFrames"],2,11]],[[1,0,1,2]],[[[{"name":"shards01-8","rect":[401,1,48,48],"offset":[0,0],"originalSize":[48,48],"capInsets":[0,0,0,0]}],[0],0,[0],[0],[0]],[[{"name":"shards01-1","rect":[51,1,48,48],"offset":[0,0],"originalSize":[48,48],"capInsets":[0,0,0,0]}],[0],0,[0],[0],[0]],[[{"name":"shards01-4","rect":[201,1,48,48],"offset":[0,0],"originalSize":[48,48],"capInsets":[0,0,0,0]}],[0],0,[0],[0],[0]],[[{"name":"shards01-2","rect":[101,1,48,48],"offset":[0,0],"originalSize":[48,48],"capInsets":[0,0,0,0]}],[0],0,[0],[0],[0]],[[{"name":"shards01-5","rect":[251,1,48,48],"offset":[0,0],"originalSize":[48,48],"capInsets":[0,0,0,0]}],[0],0,[0],[0],[0]],[[{"name":"shards01-3","rect":[151,1,48,48],"offset":[0,0],"originalSize":[48,48],"capInsets":[0,0,0,0]}],[0],0,[0],[0],[0]],[[[0,"effect_34.plist",[{},"shards01-0",6,0,"shards01-1",6,1,"shards01-2",6,2,"shards01-3",6,3,"shards01-4",6,4,"shards01-5",6,5,"shards01-6",6,6,"shards01-7",6,7,"shards01-8",6,8,"shards01-9",6,9]]],0,0,[0,0,0,0,0,0,0,0,0,0],[1,2,3,4,5,6,7,8,9,10],[1,2,3,4,5,6,7,8,9,10]],[[{"name":"shards01-0","rect":[1,1,48,48],"offset":[0,0],"originalSize":[48,48],"capInsets":[0,0,0,0]}],[0],0,[0],[0],[0]],[[{"name":"shards01-6","rect":[301,1,48,48],"offset":[0,0],"originalSize":[48,48],"capInsets":[0,0,0,0]}],[0],0,[0],[0],[0]],[[{"name":"shards01-9","rect":[451,1,48,48],"offset":[0,0],"originalSize":[48,48],"capInsets":[0,0,0,0]}],[0],0,[0],[0],[0]],[[{"name":"shards01-7","rect":[351,1,48,48],"offset":[0,0],"originalSize":[48,48],"capInsets":[0,0,0,0]}],[0],0,[0],[0],[0]]]]