[1,["bf12NF+o9ByZgUf4eoDOha","8aNfdVunBBY5Stj53pQE+q","06wgc8gVNHUJ1uX+dkBH9A","4a9wtKd4JFdr7lpX0AV0Xu","0e5tJeHnBO8qrtdYu/gBvh"],["_textureSetter","Teemo Basic emote animations sprite sheet-22","Teemo Basic emote animations sprite sheet-23","Teemo Basic emote animations sprite sheet-24","Teemo Basic emote animations sprite sheet-25"],["cc.SpriteFrame",["cc.SpriteAtlas",["_name","_spriteFrames"],2,11]],[[1,0,1,2]],[[[{"name":"Teemo Basic emote animations sprite sheet-23","rect":[35,1,32,32],"offset":[0,0],"originalSize":[32,32],"capInsets":[0,0,0,0]}],[0],0,[0],[0],[0]],[[{"name":"Teemo Basic emote animations sprite sheet-25","rect":[69,1,32,32],"offset":[0,0],"originalSize":[32,32],"capInsets":[0,0,0,0]}],[0],0,[0],[0],[0]],[[[0,"char_avatar_angery_1.plist",[{},"Teemo Basic emote animations sprite sheet-22",6,0,"Teemo Basic emote animations sprite sheet-23",6,1,"Teemo Basic emote animations sprite sheet-24",6,2,"Teemo Basic emote animations sprite sheet-25",6,3]]],0,0,[0,0,0,0],[1,2,3,4],[1,2,3,4]],[[{"name":"Teemo Basic emote animations sprite sheet-24","rect":[1,1,32,32],"offset":[0,0],"originalSize":[32,32],"capInsets":[0,0,0,0]}],[0],0,[0],[0],[0]],[[{"name":"Teemo Basic emote animations sprite sheet-22","rect":[1,1,32,32],"offset":[0,0],"originalSize":[32,32],"capInsets":[0,0,0,0]}],[0],0,[0],[0],[0]]]]