[1,["44XNgf3odIaLagYzOR5XSu","067eXdYptGb4n96EskpSxL","acIK0tg31Kt7M0L7UWNepn","141v7l28hGP4+mJUTolZPF","cdF47bwK5Aw6XGepRcL3mG","dcFS+RkxZAz73VVbFu0zNG","f1scKoFRlCFLJ589dMC87Z","5f+0TCVI5OO6CPDvqlfSaX","40QzeKa99MW4uOvZ5in+kb","05MAwAIdBDO5+PLecN7Zek","b9e4I6hUxKa7/GBUb3noaD","a8NoxhbzhFU4hc59wdu0w8","0c5ddvIuBEVowr6bHn22kX","6fQT0ouQNM+KWSMKMnb6RK","edatGTj5FPSKo3zAiqqy+v","e20JXzeMhIiLgIfJpAND7J","bfFo8TkPNNxbYLoSnQBJyK","246OUsaoVLLaBNDo5QFuZb","e0ILPoguJCgKcxR5oTI7l1","7ebY73I6ROTI18NbR3XzwE","ef/0H2tTtH1pc5pjSvU1Nj","eerYnbqadOob7f/wHXzmA0","e9jdYQWtZH0YGi19fhvRRx","84U2wenXhDq7gIuHSuGhJ5","75YYma+ExCCbrfnCHzweiE","3cF3d5XMNFQq83JGEHt/MN","baJFEWdHZP06+VSGeMF79Y","c60dIjEUtKiYpqSDB4ATKA","d5jwK8XzBMWYJtYZdoe6kC","634ZyPVlpAmaqKRK9e9lci","41YKcTN1RIK7w7iXaPmWSM","afU3M9ag5DrbWA8j5m7/mf","0an8M8jytKVaeK0Sbxji6E","beX6wnDndJPYZg7twAoxH5","86gKJgBGVNIqcWFD/4TXy6","c6H/Lr+DNPQoqgfg8lGE8E","53t6q0ZsNNBJGHUQqpyqt5","a4Ox2s/1NI1o4tKhT2fdLe","a0Z0GNGRlJ8KLir0VHsD4l","6fMlpvYBFEEpXM3SPnj/lh","8duuF79oJHU630f1EQ9Oyx","8dpGvB1vZDxaG4MJDF1JTn","fcg8ym7x5LeY7qzVeLYzsy","1956GG3pNM5pWge8QPOjFi","74yrx6OzpHUohj/1DLBw4K"],["_textureSetter","Explosion_2_64x64-0","Explosion_2_64x64-1","Explosion_2_64x64-10","Explosion_2_64x64-11","Explosion_2_64x64-12","Explosion_2_64x64-13","Explosion_2_64x64-14","Explosion_2_64x64-15","Explosion_2_64x64-16","Explosion_2_64x64-17","Explosion_2_64x64-18","Explosion_2_64x64-19","Explosion_2_64x64-2","Explosion_2_64x64-20","Explosion_2_64x64-21","Explosion_2_64x64-22","Explosion_2_64x64-23","Explosion_2_64x64-24","Explosion_2_64x64-25","Explosion_2_64x64-26","Explosion_2_64x64-27","Explosion_2_64x64-28","Explosion_2_64x64-29","Explosion_2_64x64-3","Explosion_2_64x64-30","Explosion_2_64x64-31","Explosion_2_64x64-32","Explosion_2_64x64-33","Explosion_2_64x64-34","Explosion_2_64x64-35","Explosion_2_64x64-36","Explosion_2_64x64-37","Explosion_2_64x64-38","Explosion_2_64x64-39","Explosion_2_64x64-4","Explosion_2_64x64-40","Explosion_2_64x64-41","Explosion_2_64x64-42","Explosion_2_64x64-43","Explosion_2_64x64-5","Explosion_2_64x64-6","Explosion_2_64x64-7","Explosion_2_64x64-8","Explosion_2_64x64-9"],["cc.SpriteFrame",["cc.SpriteAtlas",["_name","_spriteFrames"],2,11]],[[1,0,1,2]],[[[{"name":"Explosion_2_64x64-16","rect":[133,1,64,64],"offset":[0,0],"originalSize":[64,64],"capInsets":[0,0,0,0]}],[0],0,[0],[0],[0]],[[{"name":"Explosion_2_64x64-0","rect":[1,1,64,64],"offset":[0,0],"originalSize":[64,64],"capInsets":[0,0,0,0]}],[0],0,[0],[0],[0]],[[{"name":"Explosion_2_64x64-37","rect":[331,133,64,64],"offset":[0,0],"originalSize":[64,64],"capInsets":[0,0,0,0]}],[0],0,[0],[0],[0]],[[{"name":"Explosion_2_64x64-19","rect":[331,1,64,64],"offset":[0,0],"originalSize":[64,64],"capInsets":[0,0,0,0]}],[0],0,[0],[0],[0]],[[{"name":"Explosion_2_64x64-10","rect":[1,133,64,64],"offset":[0,0],"originalSize":[64,64],"capInsets":[0,0,0,0]}],[0],0,[0],[0],[0]],[[{"name":"Explosion_2_64x64-8","rect":[265,397,64,64],"offset":[0,0],"originalSize":[64,64],"capInsets":[0,0,0,0]}],[0],0,[0],[0],[0]],[[{"name":"Explosion_2_64x64-23","rect":[67,265,64,64],"offset":[0,0],"originalSize":[64,64],"capInsets":[0,0,0,0]}],[0],0,[0],[0],[0]],[[{"name":"Explosion_2_64x64-30","rect":[133,133,64,64],"offset":[0,0],"originalSize":[64,64],"capInsets":[0,0,0,0]}],[0],0,[0],[0],[0]],[[{"name":"Explosion_2_64x64-15","rect":[67,1,64,64],"offset":[0,0],"originalSize":[64,64],"capInsets":[0,0,0,0]}],[0],0,[0],[0],[0]],[[{"name":"Explosion_2_64x64-35","rect":[199,133,64,64],"offset":[0,0],"originalSize":[64,64],"capInsets":[0,0,0,0]}],[0],0,[0],[0],[0]],[[{"name":"Explosion_2_64x64-40","rect":[199,331,64,64],"offset":[0,0],"originalSize":[64,64],"capInsets":[0,0,0,0]}],[0],0,[0],[0],[0]],[[{"name":"Explosion_2_64x64-14","rect":[1,397,64,64],"offset":[0,0],"originalSize":[64,64],"capInsets":[0,0,0,0]}],[0],0,[0],[0],[0]],[[{"name":"Explosion_2_64x64-34","rect":[133,397,64,64],"offset":[0,0],"originalSize":[64,64],"capInsets":[0,0,0,0]}],[0],0,[0],[0],[0]],[[{"name":"Explosion_2_64x64-43","rect":[331,199,64,64],"offset":[0,0],"originalSize":[64,64],"capInsets":[0,0,0,0]}],[0],0,[0],[0],[0]],[[{"name":"Explosion_2_64x64-2","rect":[397,1,64,64],"offset":[0,0],"originalSize":[64,64],"capInsets":[0,0,0,0]}],[0],0,[0],[0],[0]],[[{"name":"Explosion_2_64x64-9","rect":[331,265,64,64],"offset":[0,0],"originalSize":[64,64],"capInsets":[0,0,0,0]}],[0],0,[0],[0],[0]],[[{"name":"Explosion_2_64x64-3","rect":[397,67,64,64],"offset":[0,0],"originalSize":[64,64],"capInsets":[0,0,0,0]}],[0],0,[0],[0],[0]],[[{"name":"Explosion_2_64x64-25","rect":[67,397,64,64],"offset":[0,0],"originalSize":[64,64],"capInsets":[0,0,0,0]}],[0],0,[0],[0],[0]],[[{"name":"Explosion_2_64x64-29","rect":[331,67,64,64],"offset":[0,0],"originalSize":[64,64],"capInsets":[0,0,0,0]}],[0],0,[0],[0],[0]],[[{"name":"Explosion_2_64x64-39","rect":[199,199,64,64],"offset":[0,0],"originalSize":[64,64],"capInsets":[0,0,0,0]}],[0],0,[0],[0],[0]],[[{"name":"Explosion_2_64x64-6","rect":[265,265,64,64],"offset":[0,0],"originalSize":[64,64],"capInsets":[0,0,0,0]}],[0],0,[0],[0],[0]],[[{"name":"Explosion_2_64x64-5","rect":[397,199,64,64],"offset":[0,0],"originalSize":[64,64],"capInsets":[0,0,0,0]}],[0],0,[0],[0],[0]],[[{"name":"Explosion_2_64x64-42","rect":[265,199,64,64],"offset":[0,0],"originalSize":[64,64],"capInsets":[0,0,0,0]}],[0],0,[0],[0],[0]],[[{"name":"Explosion_2_64x64-41","rect":[199,397,64,64],"offset":[0,0],"originalSize":[64,64],"capInsets":[0,0,0,0]}],[0],0,[0],[0],[0]],[[{"name":"Explosion_2_64x64-18","rect":[265,1,64,64],"offset":[0,0],"originalSize":[64,64],"capInsets":[0,0,0,0]}],[0],0,[0],[0],[0]],[[{"name":"Explosion_2_64x64-1","rect":[1,67,64,64],"offset":[0,0],"originalSize":[64,64],"capInsets":[0,0,0,0]}],[0],0,[0],[0],[0]],[[{"name":"Explosion_2_64x64-36","rect":[265,133,64,64],"offset":[0,0],"originalSize":[64,64],"capInsets":[0,0,0,0]}],[0],0,[0],[0],[0]],[[{"name":"Explosion_2_64x64-17","rect":[199,1,64,64],"offset":[0,0],"originalSize":[64,64],"capInsets":[0,0,0,0]}],[0],0,[0],[0],[0]],[[{"name":"Explosion_2_64x64-31","rect":[133,199,64,64],"offset":[0,0],"originalSize":[64,64],"capInsets":[0,0,0,0]}],[0],0,[0],[0],[0]],[[{"name":"Explosion_2_64x64-38","rect":[397,133,64,64],"offset":[0,0],"originalSize":[64,64],"capInsets":[0,0,0,0]}],[0],0,[0],[0],[0]],[[{"name":"Explosion_2_64x64-22","rect":[67,199,64,64],"offset":[0,0],"originalSize":[64,64],"capInsets":[0,0,0,0]}],[0],0,[0],[0],[0]],[[{"name":"Explosion_2_64x64-4","rect":[199,265,64,64],"offset":[0,0],"originalSize":[64,64],"capInsets":[0,0,0,0]}],[0],0,[0],[0],[0]],[[{"name":"Explosion_2_64x64-32","rect":[133,265,64,64],"offset":[0,0],"originalSize":[64,64],"capInsets":[0,0,0,0]}],[0],0,[0],[0],[0]],[[[0,"effect_60.plist",[{},"Explosion_2_64x64-0",6,0,"Explosion_2_64x64-1",6,1,"Explosion_2_64x64-10",6,2,"Explosion_2_64x64-11",6,3,"Explosion_2_64x64-12",6,4,"Explosion_2_64x64-13",6,5,"Explosion_2_64x64-14",6,6,"Explosion_2_64x64-15",6,7,"Explosion_2_64x64-16",6,8,"Explosion_2_64x64-17",6,9,"Explosion_2_64x64-18",6,10,"Explosion_2_64x64-19",6,11,"Explosion_2_64x64-2",6,12,"Explosion_2_64x64-20",6,13,"Explosion_2_64x64-21",6,14,"Explosion_2_64x64-22",6,15,"Explosion_2_64x64-23",6,16,"Explosion_2_64x64-24",6,17,"Explosion_2_64x64-25",6,18,"Explosion_2_64x64-26",6,19,"Explosion_2_64x64-27",6,20,"Explosion_2_64x64-28",6,21,"Explosion_2_64x64-29",6,22,"Explosion_2_64x64-3",6,23,"Explosion_2_64x64-30",6,24,"Explosion_2_64x64-31",6,25,"Explosion_2_64x64-32",6,26,"Explosion_2_64x64-33",6,27,"Explosion_2_64x64-34",6,28,"Explosion_2_64x64-35",6,29,"Explosion_2_64x64-36",6,30,"Explosion_2_64x64-37",6,31,"Explosion_2_64x64-38",6,32,"Explosion_2_64x64-39",6,33,"Explosion_2_64x64-4",6,34,"Explosion_2_64x64-40",6,35,"Explosion_2_64x64-41",6,36,"Explosion_2_64x64-42",6,37,"Explosion_2_64x64-43",6,38,"Explosion_2_64x64-5",6,39,"Explosion_2_64x64-6",6,40,"Explosion_2_64x64-7",6,41,"Explosion_2_64x64-8",6,42,"Explosion_2_64x64-9",6,43]]],0,0,[0,0,0,0,0,0,0,0,0,0,0,0,0,0,0,0,0,0,0,0,0,0,0,0,0,0,0,0,0,0,0,0,0,0,0,0,0,0,0,0,0,0,0,0],[1,2,3,4,5,6,7,8,9,10,11,12,13,14,15,16,17,18,19,20,21,22,23,24,25,26,27,28,29,30,31,32,33,34,35,36,37,38,39,40,41,42,43,44],[1,2,3,4,5,6,7,8,9,10,11,12,13,14,15,16,17,18,19,20,21,22,23,24,25,26,27,28,29,30,31,32,33,34,35,36,37,38,39,40,41,42,43,44]],[[{"name":"Explosion_2_64x64-11","rect":[1,199,64,64],"offset":[0,0],"originalSize":[64,64],"capInsets":[0,0,0,0]}],[0],0,[0],[0],[0]],[[{"name":"Explosion_2_64x64-33","rect":[133,331,64,64],"offset":[0,0],"originalSize":[64,64],"capInsets":[0,0,0,0]}],[0],0,[0],[0],[0]],[[{"name":"Explosion_2_64x64-12","rect":[1,265,64,64],"offset":[0,0],"originalSize":[64,64],"capInsets":[0,0,0,0]}],[0],0,[0],[0],[0]],[[{"name":"Explosion_2_64x64-24","rect":[67,331,64,64],"offset":[0,0],"originalSize":[64,64],"capInsets":[0,0,0,0]}],[0],0,[0],[0],[0]],[[{"name":"Explosion_2_64x64-21","rect":[67,133,64,64],"offset":[0,0],"originalSize":[64,64],"capInsets":[0,0,0,0]}],[0],0,[0],[0],[0]],[[{"name":"Explosion_2_64x64-28","rect":[265,67,64,64],"offset":[0,0],"originalSize":[64,64],"capInsets":[0,0,0,0]}],[0],0,[0],[0],[0]],[[{"name":"Explosion_2_64x64-20","rect":[67,67,64,64],"offset":[0,0],"originalSize":[64,64],"capInsets":[0,0,0,0]}],[0],0,[0],[0],[0]],[[{"name":"Explosion_2_64x64-27","rect":[199,67,64,64],"offset":[0,0],"originalSize":[64,64],"capInsets":[0,0,0,0]}],[0],0,[0],[0],[0]],[[{"name":"Explosion_2_64x64-26","rect":[133,67,64,64],"offset":[0,0],"originalSize":[64,64],"capInsets":[0,0,0,0]}],[0],0,[0],[0],[0]],[[{"name":"Explosion_2_64x64-13","rect":[1,331,64,64],"offset":[0,0],"originalSize":[64,64],"capInsets":[0,0,0,0]}],[0],0,[0],[0],[0]],[[{"name":"Explosion_2_64x64-7","rect":[265,331,64,64],"offset":[0,0],"originalSize":[64,64],"capInsets":[0,0,0,0]}],[0],0,[0],[0],[0]]]]