[1,0,0,[["cc.JsonAsset",["_name","json"],1]],[[0,0,1,3]],[[0,"skill",{"1":{"id":"1","name":"体力增强","dec":"最大体力上升10","type":1,"index":1,"num":null,"param":{"maxHealth":10}},"2":{"id":"2","name":"恢复增强","dec":"每天额外恢复5%最大体力值","type":3,"index":2,"num":null,"param":{"daliyHealth":5}},"3":{"id":"3","name":"有中生有","dec":"收获时有概率多收获一个作物","type":1,"index":8,"param":null,"num":null},"4":{"id":"4","name":"农业专家","dec":"收获非连续作物的时候有概率获得种子","type":1,"index":3,"param":null,"num":null},"5":{"id":"5","name":"武器附魔","dec":"对同伴使用武器强化时效果更好","type":2,"index":5,"num":null,"param":{"friendWeapon":1}},"6":{"id":"6","name":"买它","dec":"售卖时有概率额外出售一个","type":3,"index":7,"param":null,"num":null},"7":{"id":"7","name":"农夫","dec":"开垦时有概率获得种子","type":1,"index":5,"param":null,"num":null},"8":{"id":"8","name":"高级诱饵","dec":"钓鱼获得的物品品质上升","type":3,"index":5,"num":null,"param":{"fishQuality":1}},"9":{"id":"9","name":"勘探","dec":"探索时更容易获得更高品质的物品","type":2,"index":7,"num":null,"param":{"exploreQuality":1}},"10":{"id":"10","name":"幸运星","dec":"打开宝箱时的奖励更好","type":2,"index":4,"param":null,"num":null},"11":{"id":"11","name":"乐于助人","dec":"完成委托的奖励提升","type":2,"index":3,"num":null,"param":{"questReward":15}},"12":{"id":"12","name":"特邀嘉宾","dec":"每月收到公会寄来的武器","type":2,"index":5,"param":null,"num":null},"13":{"id":"13","name":"谁啊","dec":"每月收到朋友寄来的特产","type":2,"index":6,"param":null,"num":null},"14":{"id":"14","name":"有机蔬菜","dec":"蔬菜的售价提升10%","type":1,"index":1,"num":null,"param":{"type3Price":10}},"15":{"id":"15","name":"有机水果","dec":"水果的售价提升10%","type":1,"index":2,"num":null,"param":{"type4Price":10}},"16":{"id":"16","name":"魅力四射","dec":"给朋友送花时获得的好感上升","type":2,"index":4,"num":null,"param":{"friendFlower":1}},"17":{"id":"17","name":"高级牧草","dec":"动物副产品的物品售价提升20%","type":3,"index":1,"num":null,"param":{"type8Price":20}},"18":{"id":"18","name":"加价15%","dec":"料理的售价提升15%","type":1,"index":5,"num":null,"param":{"type16Price":15,"type17Price":15}},"19":{"id":"19","name":"药物处理","dec":"肥料的效果提升25%","type":1,"index":6,"num":null,"param":{"fertEffect":25}},"20":{"id":"20","name":"飞速学习","dec":"生活技能学习速度加快10%","type":3,"index":1,"num":null,"param":{"planSkillExp":10}},"21":{"id":"21","name":"作物改良","dec":"作物的售价提升10%","type":1,"index":7,"num":null,"param":{"type12Price":10}},"22":{"id":"22","name":"vip","dec":"每月会收到商店寄来的种子","type":1,"index":3,"param":null,"num":null},"23":{"id":"23","name":"批发商","dec":"商店的种子价格下降10%","type":1,"index":6,"num":null,"param":{"seedPrice":-10}},"24":{"id":"24","name":"恩赐","dec":"副产品产出的数量上升1","type":3,"index":9,"num":null,"param":{"animalProduct":1}},"25":{"id":"25","name":"委托大师","dec":"每月的委托数量变多","type":2,"index":2,"num":null,"param":{"questNum":1}},"26":{"id":"26","name":"种子提取","dec":"可以从每个农作物中提取三个同品质种子","type":1,"index":7,"param":null,"num":null},"27":{"id":"27","name":"量大管饱","dec":"手动制作料理时额外获得一份","type":3,"index":9,"param":null,"num":null},"28":{"id":"28","name":"美味加倍","dec":"料理的恢复体力效果增加33%","type":3,"index":3,"num":null,"param":{"foodHealth":33}},"29":{"id":"29","name":"围观","dec":"根据时间增加冒险者的经验","type":2,"index":1,"param":null,"num":null},"30":{"id":"30","name":"超级幸运","dec":"幸运增加","type":3,"index":6,"num":null,"param":{"lucky":1}},"31":{"id":"31","name":"动物园","dec":"牧场里每有一只动物，每天会额外收到10金币","type":3,"index":2,"param":null,"num":null},"32":{"id":"32","name":"与动物对话","dec":"每月会收到野生动物寄来的农产品","type":3,"index":4,"param":null,"num":null},"33":{"id":"33","name":"深海区","dec":"钓鱼时获得宝藏的概率升高","type":2,"index":3,"num":null,"param":{"fishChestChance":10}},"34":{"id":"34","name":"手工作坊","dec":"开启作坊功能","type":2,"index":8,"param":null,"num":null},"35":{"id":"35","name":"重复利用","dec":"打造家具时消耗降低10%","type":3,"index":4,"num":null,"param":{"furnitureCost":-10}},"36":{"id":"36","name":"一丝不苟","dec":"可以从农田里回收种子","type":1,"index":2,"param":null,"num":null},"37":{"id":"37","name":"宝石","dec":"挖矿时获得宝石的概率上升5%","type":2,"index":7,"num":null,"param":{"mineDiamondChance":5}},"38":{"id":"38","name":"仔细搜寻","dec":"砍伐时增加获得水果和坚果的概率","type":2,"index":1,"num":null,"param":{"logFoodChance":30}},"39":{"id":"39","name":"天命","dec":"每天早上有概率增加2%金币或减少1%金币","type":3,"index":6,"param":null,"num":null},"40":{"id":"40","name":"朋友成群","dec":"每有一个朋友，增加1体力最大值","type":2,"index":2,"param":null,"num":null},"41":{"id":"41","name":"干净水域","dec":"渔网捕获的物品的品质上升","type":3,"index":8,"param":null,"num":null},"42":{"id":"42","name":"捕捞许可","dec":"渔网的最大布置量扩大到10个","type":3,"index":8,"param":null,"num":null},"43":{"id":"43","name":"画饼","dec":"冒险者的工资变低25%","type":2,"index":8,"num":null,"param":{"salaryPrecent":-25}},"44":{"id":"44","name":"匠人精神","dec":"材料出售价格上升25%","type":3,"index":5,"num":null,"param":{"type5Price":10}},"45":{"id":"45","name":"高效研磨","dec":"调味品出售价格上升25%","type":1,"index":4,"num":null,"param":{"type11Price":25}},"46":{"id":"46","name":"闪闪发光","dec":"高品质的物品出售价格上升20%","type":3,"index":7,"num":null,"param":{"qualityHighPrice":20}},"47":{"id":"47","name":"锯木切割","dec":"伐木时必定额外获得一个普通的木材","type":2,"index":6,"param":null,"num":null},"48":{"id":"48","name":"农业魔法","dec":"施肥后当月对应土壤品质不会下降","type":1,"index":8,"param":null,"num":null},"49":{"id":"49","name":"节约材料","dec":"降低15%建筑花费","type":3,"index":3,"num":null,"param":{"buildCost":-15}},"50":{"id":"50","name":"休息增强","dec":"休息额外恢复30%最大体力值","type":1,"index":4,"num":null,"param":{"relaxHealth":30}},"51":{"id":"51","name":"魔法女巫","dec":"开启魔法小屋功能","type":1,"index":9,"param":null,"num":null},"52":{"id":"52","name":"锁死","dec":"作物品质不会因为土壤品质过低而下降","type":1,"index":9,"param":null,"num":null},"101":{"id":"101","name":"飞速学习","dec":"所有人获得战斗经验提升加快{0}%","type":null,"index":null,"num":5,"param":{"expRate":0}},"102":{"id":"102","name":"持盾","dec":"敌人对队伍造成的伤害减少{0}%","type":null,"index":null,"num":-5,"param":{"dmgRate":0}},"103":{"id":"103","name":"身强体壮","dec":"队伍里所有人最大生命值上升{0}点","type":null,"index":null,"num":2,"param":{"friendMaxHp":0}},"104":{"id":"104","name":"荆棘","dec":"队伍里所有人受到伤害后反弹{0}%伤害","type":null,"index":null,"num":10,"param":{"backfire":0}},"105":{"id":"105","name":"英勇","dec":"队伍里在最前方角色，伤害上升{0}%","type":null,"index":null,"num":20,"param":{"firstAtk":0}},"106":{"id":"106","name":"快就是快","dec":"队伍里所有人攻击速度提升{0}%","type":null,"index":null,"num":5,"param":{"atkSpd":0}},"107":{"id":"107","name":"回复之手","dec":"攻击时恢复血量最少队友的{0}Hp，根据回复能力提升","type":null,"index":null,"num":5,"param":{"atkHealLowest":0}},"108":{"id":"108","name":"休息一下","dec":"为休息中的朋友提供{0}%休息速度加成","type":null,"index":null,"num":3,"param":{"relaxSpd":0}},"109":{"id":"109","name":"持续恢复","dec":"所有人每秒缓慢恢复{0}Hp，根据回复能力提升","type":null,"index":null,"num":5,"param":{"autoHeal":0}},"110":{"id":"110","name":"双重打击","dec":"队伍里所有人有{0}%概率造成双倍伤害","type":null,"index":null,"num":5,"param":{"doubleChance":0}},"111":{"id":"111","name":"诅咒","dec":"敌人的攻击速度下降{0}%","type":null,"index":null,"num":-10,"param":{"ememyAtkSpd":0}},"112":{"id":"112","name":"恢复打击","dec":"队伍里所有人攻击时回复{0}%造成的伤害的生命值","type":null,"index":null,"num":10,"param":{"atkSelfHeal":0}},"113":{"id":"113","name":"致盲","dec":"队伍里所有人有{0}%概率躲避伤害","type":null,"index":null,"num":3,"param":{"dadgeChance":0}},"114":{"id":"114","name":"攻击！","dec":"所有人攻击能力提升{0}","type":null,"index":null,"num":2,"param":{"point1Add":0}},"115":{"id":"115","name":"防御！","dec":"所有人防御能力提升{0}","type":null,"index":null,"num":2,"param":{"point2Add":0}},"116":{"id":"116","name":"回复！","dec":"所有人回复能力提升{0}","type":null,"index":null,"num":2,"param":{"point3Add":0}},"117":{"id":"117","name":"坚持不懈","dec":"队伍里所有人有{0}%概率抵抗破防","type":null,"index":null,"num":5,"param":{"resistDeathChance":0}},"118":{"id":"118","name":"无人知晓","dec":"击败敌人获得物品概率提升{0}%","type":null,"index":null,"num":3,"param":{"dropChanceAdd":0}},"119":{"id":"119","name":"皇家防御","dec":"队伍里所有人受到的超过自身血量最大值10%的伤害将会被抹去，最低1","type":null,"index":null,"param":null,"num":0},"120":{"id":"120","name":"冰属性武器","dec":"队伍里所有人攻击时额外附带{0}伤害","type":null,"index":null,"num":10,"param":{"moreAtk":0}},"121":{"id":"121","name":"反抗精神","dec":"队伍里所有人生命值低于30%时伤害提升{0}%","type":null,"index":null,"num":25,"param":{"Hp30AtkAdd":0}},"122":{"id":"122","name":"慢就是快","dec":"队伍里所有人攻击速度下降15%，伤害上升50%","type":null,"index":null,"num":0,"param":{"atkSpd":-15,"atkRate":50}},"123":{"id":"123","name":"一命通关","dec":"当前角色，血量最大值为1，但是攻击力是五倍","type":null,"index":null,"param":null,"num":0},"124":{"id":"124","name":"患难与共","dec":"队伍里所有人攻击速度下降15%，队伍里所有人会共同承担伤害","type":null,"index":null,"num":0,"param":{"atkSpd":-15}},"125":{"id":"125","name":"精准","dec":"队伍里所有人对动物额外造成{0}%伤害","type":null,"index":null,"num":25,"param":{"animalAtk":0}},"126":{"id":"126","name":"双击","dec":"队伍里所有人攻击时有{0}%概率在攻击后再攻击一次","type":null,"index":null,"num":5,"param":{"twiceAtk":0}},"127":{"id":"127","name":"荣耀","dec":"击杀敌人后获得的点数奖励上升{0}%","type":null,"index":null,"num":4,"param":{"pointReward":0}},"128":{"id":"128","name":"精力充沛","dec":"所有朋友增加最大体力值{0}点","type":null,"index":null,"num":5,"param":{"point4Add":0}},"129":{"id":"129","name":"斥候","dec":"探索地图的速度加快{0}%","type":null,"index":null,"num":4,"param":{"exploreSpd":0}},"130":{"id":"130","name":"土地感知","dec":"所有人伐木速度上升{0}%","type":null,"index":null,"num":4,"param":{"find2Spd":0}},"131":{"id":"131","name":"快速移动","dec":"所有人觅食速度上升{0}%","type":null,"index":null,"num":4,"param":{"find1Spd":0}},"132":{"id":"132","name":"高温挖掘","dec":"所有人采掘速度上升{0}%","type":null,"index":null,"num":4,"param":{"find3Spd":0}},"133":{"id":"133","name":"高级鱼线","dec":"所有人钓鱼速度上升{0}%","type":null,"index":null,"num":4,"param":{"find4Spd":0}},"134":{"id":"134","name":"植物魔法","dec":"所有人伐木获得的奖励有{0}%概率翻倍","type":null,"index":null,"num":10,"param":{"find2Double":0}},"135":{"id":"135","name":"指引","dec":"所有人觅食获得的奖励有{0}%概率翻倍","type":null,"index":null,"num":10,"param":{"find1Double":0}},"136":{"id":"136","name":"武器变大","dec":"所有人采掘获得的奖励有{0}%概率翻倍","type":null,"index":null,"num":10,"param":{"find3Double":0}},"137":{"id":"137","name":"鱼语","dec":"所有人钓鱼获得的奖励有{0}%概率翻倍","type":null,"index":null,"num":10,"param":{"find4Double":0}},"138":{"id":"138","name":"为爱发电","dec":"不需要付工资就可以帮你干活！","type":null,"index":null,"param":null,"num":null},"139":{"id":"139","name":"招揽顾客","dec":"顾客数量上升{0}%","type":null,"index":null,"num":3,"param":{"costomerNum":0}},"140":{"id":"140","name":"反击","dec":"所有人受到攻击后{0}%概率立马攻击一次","type":null,"index":null,"num":5,"param":{"fightBack":0}},"141":{"id":"141","name":"搅拌","dec":"饲料的转化率增加{0}%","type":null,"index":null,"num":10,"param":{"grassRate":0}},"142":{"id":"142","name":"点金术","dec":"击败敌人也能获得金钱","type":null,"index":null,"param":null,"num":0},"143":{"id":"143","name":"内部价格","dec":"公会商店的价格下降{0}%","type":null,"index":null,"num":-3,"param":{"advShopPrice":0}},"144":{"id":"144","name":"交易师","dec":"售卖价格提升{0}%","type":null,"index":null,"num":3,"param":{"salePrice":0}},"145":{"id":"145","name":"土壤学","dec":"每天为土地增加土壤品质","type":null,"index":null,"num":10,"param":{"daliySoildQua":0}},"146":{"id":"146","name":"水魔法师","dec":"每天为土地增加土壤保湿概率","type":null,"index":null,"num":10,"param":{"dailySoildWater":0}},"147":{"id":"147","name":"高速运转","dec":"作坊的生产速度加快{0}%","type":null,"index":null,"num":3,"param":{"factorySpd":0}},"148":{"id":"148","name":"仔细剥离","dec":"得到战利品的品质有{0}%概率上升","type":null,"index":null,"num":3,"param":{"dropQuaChance":0}},"149":{"id":"149","name":"精心照料","dec":"动物生产时间加快{0}%","type":null,"index":null,"num":3,"param":{"animalProductSpd":0}},"150":{"id":"150","name":"冰魔法师","dec":"水产品价格上升{0}%","type":null,"index":null,"num":10,"param":{"type22Price":0}},"201":{"id":"201","name":"前排","dec":"优先攻击一号位","type":null,"index":null,"param":null,"num":null},"202":{"id":"202","name":"中程","dec":"优先攻击二号位","type":null,"index":null,"param":null,"num":null},"203":{"id":"203","name":"远程","dec":"优先攻击三号位","type":null,"index":null,"param":null,"num":null},"204":{"id":"204","name":"连击","dec":"攻击两个目标","type":null,"index":null,"param":null,"num":null},"205":{"id":"205","name":"范围","dec":"攻击三个目标","type":null,"index":null,"param":null,"num":null},"206":{"id":"206","name":"实物","dec":"无法攻击","type":null,"index":null,"param":null,"num":null},"null":{"id":null,"name":null,"dec":null,"type":null,"index":null,"param":null,"num":null},"怪物 特质":{"id":"怪物 特质","name":null,"dec":null,"type":null,"index":null,"param":null,"num":null},"朋友 - 技能":{"id":"朋友 - 技能","name":null,"dec":null,"type":null,"index":null,"param":null,"num":null}}]],0,0,[],[],[]]